{
    "features": [
        {
            "properties": {
                "marker-color": "#d7eed1",
                "datetime": "2017-10-26T05:38:00Z",
                "img_name": "IMG_3664.JPG",
                "marker-symbol": "heart",
                "value": "46"
            },
            "type": "Feature",
            "geometry": {
                "type": "Point",
                "coordinates": [
                    106.83194444444445,
                    -6.180555555555556
                ]
            }
        },
        {
            "properties": {
                "marker-color": "#d7eed1",
                "datetime": "2017-10-26T05:38:30Z",
                "img_name": "IMG_3665.JPG",
                "marker-symbol": "heart",
                "value": "46"
            },
            "type": "Feature",
            "geometry": {
                "type": "Point",
                "coordinates": [
                    106.83194444444445,
                    -6.180277777777778
                ]
            }
        },
        {
            "properties": {
                "marker-color": "#d7eed1",
                "datetime": "2017-10-26T05:38:31Z",
                "img_name": "IMG_3666.JPG",
                "marker-symbol": "heart",
                "value": "46"
            },
            "type": "Feature",
            "geometry": {
                "type": "Point",
                "coordinates": [
                    106.83194444444445,
                    -6.180277777777778
                ]
            }
        },
        {
            "properties": {
                "marker-color": "#e1f2d2",
                "datetime": "2017-10-26T05:52:54Z",
                "img_name": "IMG_3673(1).JPG",
                "marker-symbol": "heart",
                "value": "57"
            },
            "type": "Feature",
            "geometry": {
                "type": "Point",
                "coordinates": [
                    106.83222222222221,
                    -6.180277777777778
                ]
            }
        },
        {
            "properties": {
                "marker-color": "#e1f2d2",
                "datetime": "2017-10-26T05:52:54Z",
                "img_name": "IMG_3673.JPG",
                "marker-symbol": "heart",
                "value": "57"
            },
            "type": "Feature",
            "geometry": {
                "type": "Point",
                "coordinates": [
                    106.83222222222221,
                    -6.180277777777778
                ]
            }
        },
        {
            "properties": {
                "marker-color": "#efbdbe",
                "datetime": "2017-10-29T00:45:26Z",
                "img_name": "IMG_3709.jpg",
                "marker-symbol": "heart",
                "value": "185"
            },
            "type": "Feature",
            "geometry": {
                "type": "Point",
                "coordinates": [
                    106.82222222222222,
                    -6.207777777777778
                ]
            }
        },
        {
            "properties": {},
            "type": "Feature",
            "geometry": {
                "type": "LineString",
                "coordinates": [
                    [
                        106.82194444444444,
                        -6.2075000000000005
                    ],
                    [
                        116.14082149927766,
                        -2.580031125301991
                    ]
                ]
            }
        },
        {
            "properties": {},
            "type": "Feature",
            "geometry": {
                "type": "LineString",
                "coordinates": [
                    [
                        106.82222222222222,
                        -6.207777777777778
                    ],
                    [
                        99.74186715998584,
                        0.8539905696450969
                    ]
                ]
            }
        },
        {
            "properties": {},
            "type": "Feature",
            "geometry": {
                "type": "LineString",
                "coordinates": [
                    [
                        106.82222222222222,
                        -6.207777777777778
                    ],
                    [
                        116.57459853662989,
                        -3.9961819236081606
                    ]
                ]
            }
        },
        {
            "properties": {
                "marker-color": "#f5c5c0",
                "datetime": "2017-10-29T01:12:04Z",
                "img_name": "IMG_3730.jpg",
                "marker-symbol": "heart",
                "value": "175"
            },
            "type": "Feature",
            "geometry": {
                "type": "Point",
                "coordinates": [
                    106.82277777777777,
                    -6.203055555555555
                ]
            }
        },
        {
            "properties": {
                "marker-color": "#f2bfbe",
                "datetime": "2017-10-29T01:14:33Z",
                "img_name": "IMG_3731.JPG",
                "marker-symbol": "heart",
                "value": "182"
            },
            "type": "Feature",
            "geometry": {
                "type": "Point",
                "coordinates": [
                    106.82277777777777,
                    -6.203055555555555
                ]
            }
        },
        {
            "properties": {
                "marker-color": "#f2bfbe",
                "datetime": "2017-10-29T01:14:36Z",
                "img_name": "IMG_3732.JPG",
                "marker-symbol": "heart",
                "value": "182"
            },
            "type": "Feature",
            "geometry": {
                "type": "Point",
                "coordinates": [
                    106.82277777777777,
                    -6.203055555555555
                ]
            }
        },
        {
            "properties": {
                "marker-color": "#facfc5",
                "datetime": "2017-10-29T01:44:33Z",
                "img_name": "IMG_3743.JPG",
                "marker-symbol": "heart",
                "value": "165"
            },
            "type": "Feature",
            "geometry": {
                "type": "Point",
                "coordinates": [
                    106.82305555555556,
                    -6.198333333333333
                ]
            }
        },
        {
            "properties": {
                "marker-color": "#facfc5",
                "datetime": "2017-10-29T01:44:37Z",
                "img_name": "IMG_3745.JPG",
                "marker-symbol": "heart",
                "value": "165"
            },
            "type": "Feature",
            "geometry": {
                "type": "Point",
                "coordinates": [
                    106.82305555555556,
                    -6.198333333333333
                ]
            }
        },
        {
            "properties": {
                "marker-color": "#f2bfbe",
                "datetime": "2017-10-29T02:07:6Z",
                "img_name": "IMG_3747.JPG",
                "marker-symbol": "heart",
                "value": "182"
            },
            "type": "Feature",
            "geometry": {
                "type": "Point",
                "coordinates": [
                    106.8236111111111,
                    -6.194444444444445
                ]
            }
        },
        {
            "properties": {
                "marker-color": "#f2bfbe",
                "datetime": "2017-10-29T02:07:10Z",
                "img_name": "IMG_3748.JPG",
                "marker-symbol": "heart",
                "value": "182"
            },
            "type": "Feature",
            "geometry": {
                "type": "Point",
                "coordinates": [
                    106.8236111111111,
                    -6.194444444444445
                ]
            }
        },
        {
            "properties": {
                "marker-color": "#f8ccc3",
                "datetime": "2017-10-29T02:08:37Z",
                "img_name": "IMG_3749.JPG",
                "marker-symbol": "heart",
                "value": "168"
            },
            "type": "Feature",
            "geometry": {
                "type": "Point",
                "coordinates": [
                    106.8236111111111,
                    -6.1947222222222225
                ]
            }
        },
        {
            "properties": {
                "marker-color": "#fcd5c8",
                "datetime": "2017-10-29T03:08:44Z",
                "img_name": "IMG_3754.JPG",
                "marker-symbol": "heart",
                "value": "158"
            },
            "type": "Feature",
            "geometry": {
                "type": "Point",
                "coordinates": [
                    106.82222222222222,
                    -6.207777777777778
                ]
            }
        },
        {
            "properties": {
                "marker-color": "#fcd5c8",
                "datetime": "2017-10-29T03:08:50Z",
                "img_name": "IMG_3755.JPG",
                "marker-symbol": "heart",
                "value": "158"
            },
            "type": "Feature",
            "geometry": {
                "type": "Point",
                "coordinates": [
                    106.82222222222222,
                    -6.207777777777778
                ]
            }
        },
        {
            "properties": {
                "marker-color": "#ffedd5",
                "datetime": "2017-10-29T04:11:38Z",
                "img_name": "IMG_3757.JPG",
                "marker-symbol": "heart",
                "value": "132"
            },
            "type": "Feature",
            "geometry": {
                "type": "Point",
                "coordinates": [
                    106.82249999999999,
                    -6.207777777777778
                ]
            }
        },
        {
            "properties": {
                "marker-color": "#ffedd5",
                "datetime": "2017-10-29T04:11:44Z",
                "img_name": "IMG_3758.JPG",
                "marker-symbol": "heart",
                "value": "132"
            },
            "type": "Feature",
            "geometry": {
                "type": "Point",
                "coordinates": [
                    106.82249999999999,
                    -6.207777777777778
                ]
            }
        },
        {
            "properties": {
                "marker-color": "#ffedd5",
                "datetime": "2017-10-29T04:13:4Z",
                "img_name": "IMG_3759.JPG",
                "marker-symbol": "heart",
                "value": "132"
            },
            "type": "Feature",
            "geometry": {
                "type": "Point",
                "coordinates": [
                    106.82222222222222,
                    -6.207777777777778
                ]
            }
        },
        {
            "properties": {
                "marker-color": "#ffedd5",
                "datetime": "2017-10-29T04:13:16Z",
                "img_name": "IMG_3760.JPG",
                "marker-symbol": "heart",
                "value": "132"
            },
            "type": "Feature",
            "geometry": {
                "type": "Point",
                "coordinates": [
                    106.82222222222222,
                    -6.207777777777778
                ]
            }
        },
        {
            "properties": {
                "marker-color": "#ffefd7",
                "datetime": "2017-10-29T04:17:38Z",
                "img_name": "IMG_3763.JPG",
                "marker-symbol": "heart",
                "value": "129"
            },
            "type": "Feature",
            "geometry": {
                "type": "Point",
                "coordinates": [
                    106.82222222222222,
                    -6.2075000000000005
                ]
            }
        },
        {
            "properties": {
                "marker-color": "#ffefd7",
                "datetime": "2017-10-29T04:18:17Z",
                "img_name": "IMG_3764.JPG",
                "marker-symbol": "heart",
                "value": "129"
            },
            "type": "Feature",
            "geometry": {
                "type": "Point",
                "coordinates": [
                    106.82249999999999,
                    -6.207777777777778
                ]
            }
        },
        {
            "properties": {
                "marker-color": "#fcd6c8",
                "datetime": "2017-10-29T04:23:10Z",
                "img_name": "IMG_3765.JPG",
                "marker-symbol": "heart",
                "value": "157"
            },
            "type": "Feature",
            "geometry": {
                "type": "Point",
                "coordinates": [
                    106.82222222222222,
                    -6.207777777777778
                ]
            }
        },
        {
            "properties": {
                "marker-color": "#f9cec4",
                "datetime": "2017-10-29T04:44:52Z",
                "img_name": "IMG_3769.jpg",
                "marker-symbol": "heart",
                "value": "166"
            },
            "type": "Feature",
            "geometry": {
                "type": "Point",
                "coordinates": [
                    106.82222222222222,
                    -6.207777777777778
                ]
            }
        },
        {
            "properties": {
                "marker-color": "#f9cdc4",
                "datetime": "2017-10-29T05:02:12Z",
                "img_name": "IMG_3771.jpg",
                "marker-symbol": "heart",
                "value": "167"
            },
            "type": "Feature",
            "geometry": {
                "type": "Point",
                "coordinates": [
                    106.82277777777777,
                    -6.203055555555555
                ]
            }
        },
        {
            "properties": {
                "marker-color": "#f9cdc4",
                "datetime": "2017-10-29T05:02:21Z",
                "img_name": "IMG_3772.JPG",
                "marker-symbol": "heart",
                "value": "167"
            },
            "type": "Feature",
            "geometry": {
                "type": "Point",
                "coordinates": [
                    106.82277777777777,
                    -6.203055555555555
                ]
            }
        },
        {
            "properties": {
                "marker-color": "#f9cdc4",
                "datetime": "2017-10-29T05:02:51Z",
                "img_name": "IMG_3773.jpg",
                "marker-symbol": "heart",
                "value": "167"
            },
            "type": "Feature",
            "geometry": {
                "type": "Point",
                "coordinates": [
                    106.82277777777777,
                    -6.203055555555555
                ]
            }
        },
        {
            "properties": {},
            "type": "Feature",
            "geometry": {
                "type": "LineString",
                "coordinates": [
                    [
                        106.82333333333332,
                        -6.198888888888889
                    ],
                    [
                        112.16617295456075,
                        -14.651939508744562
                    ]
                ]
            }
        },
        {
            "properties": {},
            "type": "Feature",
            "geometry": {
                "type": "LineString",
                "coordinates": [
                    [
                        106.82333333333332,
                        -6.198888888888889
                    ],
                    [
                        111.15046539078146,
                        2.8164274204484974
                    ]
                ]
            }
        },
        {
            "properties": {},
            "type": "Feature",
            "geometry": {
                "type": "LineString",
                "coordinates": [
                    [
                        106.82305555555556,
                        -6.198888888888889
                    ],
                    [
                        115.29968699228046,
                        -11.50423708537205
                    ]
                ]
            }
        },
        {
            "properties": {},
            "type": "Feature",
            "geometry": {
                "type": "LineString",
                "coordinates": [
                    [
                        106.82305555555556,
                        -6.198333333333333
                    ],
                    [
                        100.39437597022085,
                        1.4614368191647689
                    ]
                ]
            }
        },
        {
            "properties": {
                "marker-color": "#f9cec4",
                "datetime": "2017-10-29T05:15:20Z",
                "img_name": "IMG_3778.jpg",
                "marker-symbol": "heart",
                "value": "166"
            },
            "type": "Feature",
            "geometry": {
                "type": "Point",
                "coordinates": [
                    106.82305555555556,
                    -6.198333333333333
                ]
            }
        },
        {
            "properties": {
                "marker-color": "#f8ccc3",
                "datetime": "2017-10-29T05:15:37Z",
                "img_name": "IMG_3779.JPG",
                "marker-symbol": "heart",
                "value": "168"
            },
            "type": "Feature",
            "geometry": {
                "type": "Point",
                "coordinates": [
                    106.82305555555556,
                    -6.198333333333333
                ]
            }
        },
        {
            "properties": {},
            "type": "Feature",
            "geometry": {
                "type": "LineString",
                "coordinates": [
                    [
                        106.8236111111111,
                        -6.194444444444445
                    ],
                    [
                        97.64897293651237,
                        -10.17263679338831
                    ]
                ]
            }
        },
        {
            "properties": {},
            "type": "Feature",
            "geometry": {
                "type": "LineString",
                "coordinates": [
                    [
                        106.8236111111111,
                        -6.1947222222222225
                    ],
                    [
                        106.64292034095044,
                        -16.193089631233494
                    ]
                ]
            }
        },
        {
            "properties": {
                "marker-color": "#f5c5c0",
                "datetime": "2017-10-29T05:49:58Z",
                "img_name": "IMG_3783.JPG",
                "marker-symbol": "heart",
                "value": "176"
            },
            "type": "Feature",
            "geometry": {
                "type": "Point",
                "coordinates": [
                    106.8236111111111,
                    -6.194444444444445
                ]
            }
        },
        {
            "properties": {
                "marker-color": "#f4c3bf",
                "datetime": "2017-10-29T05:52:02Z",
                "img_name": "IMG_3784.JPG",
                "marker-symbol": "heart",
                "value": "178"
            },
            "type": "Feature",
            "geometry": {
                "type": "Point",
                "coordinates": [
                    106.8236111111111,
                    -6.194444444444445
                ]
            }
        },
        {
            "properties": {},
            "type": "Feature",
            "geometry": {
                "type": "LineString",
                "coordinates": [
                    [
                        106.82222222222222,
                        -6.208055555555556
                    ],
                    [
                        115.56998953583897,
                        -1.3627932275883232
                    ]
                ]
            }
        },
        {
            "properties": {
                "marker-color": "#f5fbde",
                "datetime": "2017-10-30T08:45:43Z",
                "img_name": "IMG_3790.JPG",
                "marker-symbol": "heart",
                "value": "82"
            },
            "type": "Feature",
            "geometry": {
                "type": "Point",
                "coordinates": [
                    106.82194444444444,
                    -6.207777777777778
                ]
            }
        },
        {
            "properties": {
                "marker-color": "#fcd4c7",
                "datetime": "2017-10-30T09:05:16Z",
                "img_name": "IMG_3792.JPG",
                "marker-symbol": "heart",
                "value": "159"
            },
            "type": "Feature",
            "geometry": {
                "type": "Point",
                "coordinates": [
                    106.82277777777777,
                    -6.203333333333333
                ]
            }
        },
        {
            "properties": {
                "marker-color": "#fddaca",
                "datetime": "2017-10-30T09:09:40Z",
                "img_name": "IMG_3807.jpg",
                "marker-symbol": "heart",
                "value": "153"
            },
            "type": "Feature",
            "geometry": {
                "type": "Point",
                "coordinates": [
                    106.82277777777777,
                    -6.203055555555555
                ]
            }
        },
        {
            "properties": {
                "marker-color": "#fddaca",
                "datetime": "2017-10-30T09:09:40Z",
                "img_name": "IMG_3808.jpg",
                "marker-symbol": "heart",
                "value": "153"
            },
            "type": "Feature",
            "geometry": {
                "type": "Point",
                "coordinates": [
                    106.82277777777777,
                    -6.203055555555555
                ]
            }
        },
        {
            "properties": {
                "marker-color": "#fddaca",
                "datetime": "2017-10-30T09:09:41Z",
                "img_name": "IMG_3809.jpg",
                "marker-symbol": "heart",
                "value": "153"
            },
            "type": "Feature",
            "geometry": {
                "type": "Point",
                "coordinates": [
                    106.82277777777777,
                    -6.203055555555555
                ]
            }
        },
        {
            "properties": {
                "marker-color": "#fddaca",
                "datetime": "2017-10-30T09:09:49Z",
                "img_name": "IMG_3810.JPG",
                "marker-symbol": "heart",
                "value": "153"
            },
            "type": "Feature",
            "geometry": {
                "type": "Point",
                "coordinates": [
                    106.82277777777777,
                    -6.203055555555555
                ]
            }
        },
        {
            "properties": {
                "marker-color": "#fddaca",
                "datetime": "2017-10-30T09:09:59Z",
                "img_name": "IMG_3811.JPG",
                "marker-symbol": "heart",
                "value": "153"
            },
            "type": "Feature",
            "geometry": {
                "type": "Point",
                "coordinates": [
                    106.82277777777777,
                    -6.203055555555555
                ]
            }
        },
        {
            "properties": {},
            "type": "Feature",
            "geometry": {
                "type": "LineString",
                "coordinates": [
                    [
                        106.82333333333332,
                        -6.198611111111111
                    ],
                    [
                        100.39778148057431,
                        -13.861005213968596
                    ]
                ]
            }
        },
        {
            "properties": {},
            "type": "Feature",
            "geometry": {
                "type": "LineString",
                "coordinates": [
                    [
                        106.82305555555556,
                        -6.198888888888889
                    ],
                    [
                        98.00263853877819,
                        -1.4871754372723487
                    ]
                ]
            }
        },
        {
            "properties": {
                "marker-color": "#fffeea",
                "datetime": "2017-10-30T09:31:48Z",
                "img_name": "IMG_3815.JPG",
                "marker-symbol": "heart",
                "value": "102"
            },
            "type": "Feature",
            "geometry": {
                "type": "Point",
                "coordinates": [
                    106.82305555555556,
                    -6.198333333333333
                ]
            }
        },
        {
            "properties": {
                "marker-color": "#fffae4",
                "datetime": "2017-10-30T09:33:29Z",
                "img_name": "IMG_3817.JPG",
                "marker-symbol": "heart",
                "value": "110"
            },
            "type": "Feature",
            "geometry": {
                "type": "Point",
                "coordinates": [
                    106.82305555555556,
                    -6.198333333333333
                ]
            }
        },
        {
            "properties": {},
            "type": "Feature",
            "geometry": {
                "type": "LineString",
                "coordinates": [
                    [
                        106.82333333333332,
                        -6.194166666666667
                    ],
                    [
                        111.66890780962535,
                        -14.941761078543983
                    ]
                ]
            }
        },
        {
            "properties": {
                "marker-color": "#fff6dd",
                "datetime": "2017-10-30T10:00:15Z",
                "img_name": "IMG_3819.JPG",
                "marker-symbol": "heart",
                "value": "119"
            },
            "type": "Feature",
            "geometry": {
                "type": "Point",
                "coordinates": [
                    106.82333333333332,
                    -6.194444444444445
                ]
            }
        },
        {
            "properties": {},
            "type": "Feature",
            "geometry": {
                "type": "LineString",
                "coordinates": [
                    [
                        106.83194444444445,
                        -6.180555555555556
                    ],
                    [
                        106.83194444444445,
                        -6.180277777777778
                    ],
                    [
                        106.83194444444445,
                        -6.180277777777778
                    ],
                    [
                        106.83222222222221,
                        -6.180277777777778
                    ],
                    [
                        106.83222222222221,
                        -6.180277777777778
                    ],
                    [
                        106.82222222222222,
                        -6.207777777777778
                    ],
                    [
                        106.82277777777777,
                        -6.203055555555555
                    ],
                    [
                        106.82277777777777,
                        -6.203055555555555
                    ],
                    [
                        106.82277777777777,
                        -6.203055555555555
                    ],
                    [
                        106.82305555555556,
                        -6.198333333333333
                    ],
                    [
                        106.82305555555556,
                        -6.198333333333333
                    ],
                    [
                        106.8236111111111,
                        -6.194444444444445
                    ],
                    [
                        106.8236111111111,
                        -6.194444444444445
                    ],
                    [
                        106.8236111111111,
                        -6.1947222222222225
                    ],
                    [
                        106.82222222222222,
                        -6.207777777777778
                    ],
                    [
                        106.82222222222222,
                        -6.207777777777778
                    ],
                    [
                        106.82249999999999,
                        -6.207777777777778
                    ],
                    [
                        106.82249999999999,
                        -6.207777777777778
                    ],
                    [
                        106.82222222222222,
                        -6.207777777777778
                    ],
                    [
                        106.82222222222222,
                        -6.207777777777778
                    ],
                    [
                        106.82222222222222,
                        -6.2075000000000005
                    ],
                    [
                        106.82249999999999,
                        -6.207777777777778
                    ],
                    [
                        106.82222222222222,
                        -6.207777777777778
                    ],
                    [
                        106.82222222222222,
                        -6.207777777777778
                    ],
                    [
                        106.82277777777777,
                        -6.203055555555555
                    ],
                    [
                        106.82277777777777,
                        -6.203055555555555
                    ],
                    [
                        106.82277777777777,
                        -6.203055555555555
                    ],
                    [
                        106.82305555555556,
                        -6.198333333333333
                    ],
                    [
                        106.82305555555556,
                        -6.198333333333333
                    ],
                    [
                        106.8236111111111,
                        -6.194444444444445
                    ],
                    [
                        106.8236111111111,
                        -6.194444444444445
                    ],
                    [
                        106.82194444444444,
                        -6.207777777777778
                    ],
                    [
                        106.82277777777777,
                        -6.203333333333333
                    ],
                    [
                        106.82277777777777,
                        -6.203055555555555
                    ],
                    [
                        106.82277777777777,
                        -6.203055555555555
                    ],
                    [
                        106.82277777777777,
                        -6.203055555555555
                    ],
                    [
                        106.82277777777777,
                        -6.203055555555555
                    ],
                    [
                        106.82277777777777,
                        -6.203055555555555
                    ],
                    [
                        106.82305555555556,
                        -6.198333333333333
                    ],
                    [
                        106.82305555555556,
                        -6.198333333333333
                    ],
                    [
                        106.82333333333332,
                        -6.194444444444445
                    ]
                ]
            }
        }
    ],
    "type": "FeatureCollection"
}